{"type": "FeatureCollection", "features": [{"type": "Feature", "geometry": {"type": "Point", "coordinates": [-71.43972222200003, -32.53777777800002]}, "properties": {"CUT_REG": "05", "CUT_PROV": "054", "CUT_COM": "05403", "REGION": "Valpara\u00edso", "PROVINCIA": "Petorca", "COMUNA": "Papudo", "COD_CUEN": "053", "COD_SUBC": "0530", "COD_SSUBC": "05300", "NOM_SSUBC": "Costera entre Estero Ligua y Estero Catapilco", "ALIAS": "Wom", "TISO_DESCR": "Torre Auto Soportada", "SOPO_ALTUR": 37, "DTE_DIRECC": "Cerro Higueras", "STDO_DESCR": "DECRETO EXENTO NOTIFICADO", "DOC_NUMERO": "1079", "ANIO_DOC": "25/11/2010", "ELM_CODIGO": 56771, "ELM_NOMBRE": "Nextel3G33", "FRECUENCIA": 2100, "TECNOLOGIA": "UMTS", "POINT_X": -71.439722222, "POINT_Y": -32.537777778, "COD_REG": 5, "COD_PROV": 54, "COD_COM": 5403, "COD_SSUBCU": 5300}}, {"type": "Feature", "geometry": {"type": "Point", "coordinates": [-71.43972222200003, -32.53777777800002]}, "properties": {"CUT_REG": "05", "CUT_PROV": "054", "CUT_COM": "05403", "REGION": "Valpara\u00edso", "PROVINCIA": "Petorca", "COMUNA": "Papudo", "COD_CUEN": "053", "COD_SUBC": "0530", "COD_SSUBC": "05300", "NOM_SSUBC": "Costera entre Estero Ligua y Estero Catapilco", "ALIAS": "Wom", "TISO_DESCR": "Torre Auto Soportada", "SOPO_ALTUR": 37, "DTE_DIRECC": "Cerro Higueras", "STDO_DESCR": "DECRETO NOTIFICADO", "DOC_NUMERO": "63", "ANIO_DOC": "20/04/2010", "ELM_CODIGO": 56226, "ELM_NOMBRE": "NEXTEL3G33", "FRECUENCIA": 2100, "TECNOLOGIA": "GSM UMTS", "POINT_X": -71.439722222, "POINT_Y": -32.537777778, "COD_REG": 5, "COD_PROV": 54, "COD_COM": 5403, "COD_SSUBCU": 5300}}, {"type": "Feature", "geometry": {"type": "Point", "coordinates": [-71.45861111099998, -32.519444443999944]}, "properties": {"CUT_REG": "05", "CUT_PROV": "054", "CUT_COM": "05403", "REGION": "Valpara\u00edso", "PROVINCIA": "Petorca", "COMUNA": "Papudo", "COD_CUEN": "053", "COD_SUBC": "0530", "COD_SSUBC": "05300", "NOM_SSUBC": "Costera entre Estero Ligua y Estero Catapilco", "ALIAS": "ENTEL PCS", "TISO_DESCR": "Torre Ventada", "SOPO_ALTUR": 42, "DTE_DIRECC": "FUNDO SAN CARLOS S/N", "STDO_DESCR": "DECRETO NOTIFICADO", "DOC_NUMERO": "902", "ANIO_DOC": "04/10/2007", "ELM_CODIGO": 32241, "ELM_NOMBRE": "Ruta Zapallar", "FRECUENCIA": 1900, "TECNOLOGIA": "GSM", "POINT_X": -71.458611111, "POINT_Y": -32.519444444, "COD_REG": 5, "COD_PROV": 54, "COD_COM": 5403, "COD_SSUBCU": 5300}}, {"type": "Feature", "geometry": {"type": "Point", "coordinates": [-71.45861111099998, -32.519444443999944]}, "properties": {"CUT_REG": "05", "CUT_PROV": "054", "CUT_COM": "05403", "REGION": "Valpara\u00edso", "PROVINCIA": "Petorca", "COMUNA": "Papudo", "COD_CUEN": "053", "COD_SUBC": "0530", "COD_SSUBC": "05300", "NOM_SSUBC": "Costera entre Estero Ligua y Estero Catapilco", "ALIAS": "ENTEL PCS", "TISO_DESCR": "Torre Ventada", "SOPO_ALTUR": 42, "DTE_DIRECC": "CERRO PUNTA PITE", "STDO_DESCR": "DECRETO NOTIFICADO", "DOC_NUMERO": "586", "ANIO_DOC": "11/07/2008", "ELM_CODIGO": 21744, "ELM_NOMBRE": "Ruta Zapallar Papudo 2", "FRECUENCIA": 0, "TECNOLOGIA": "", "POINT_X": -71.458611111, "POINT_Y": -32.519444444, "COD_REG": 5, "COD_PROV": 54, "COD_COM": 5403, "COD_SSUBCU": 5300}}, {"type": "Feature", "geometry": {"type": "Point", "coordinates": [-71.45861111099998, -32.519444443999944]}, "properties": {"CUT_REG": "05", "CUT_PROV": "054", "CUT_COM": "05403", "REGION": "Valpara\u00edso", "PROVINCIA": "Petorca", "COMUNA": "Papudo", "COD_CUEN": "053", "COD_SUBC": "0530", "COD_SSUBC": "05300", "NOM_SSUBC": "Costera entre Estero Ligua y Estero Catapilco", "ALIAS": "ENTEL PCS", "TISO_DESCR": "Torre Ventada", "SOPO_ALTUR": 42, "DTE_DIRECC": "FUNDO SAN CARLOS S/N", "STDO_DESCR": "DECRETO NOTIFICADO", "DOC_NUMERO": "994", "ANIO_DOC": "22/10/2007", "ELM_CODIGO": 32260, "ELM_NOMBRE": "Ruta Zapallar Papudo 2, Alt. 2", "FRECUENCIA": 1900, "TECNOLOGIA": "GSM", "POINT_X": -71.458611111, "POINT_Y": -32.519444444, "COD_REG": 5, "COD_PROV": 54, "COD_COM": 5403, "COD_SSUBCU": 5300}}, {"type": "Feature", "geometry": {"type": "Point", "coordinates": [-71.45861111099998, -32.519444443999944]}, "properties": {"CUT_REG": "05", "CUT_PROV": "054", "CUT_COM": "05403", "REGION": "Valpara\u00edso", "PROVINCIA": "Petorca", "COMUNA": "Papudo", "COD_CUEN": "053", "COD_SUBC": "0530", "COD_SSUBC": "05300", "NOM_SSUBC": "Costera entre Estero Ligua y Estero Catapilco", "ALIAS": "WILL", "TISO_DESCR": "Torre Ventada", "SOPO_ALTUR": 42, "DTE_DIRECC": "Fundo San Carlos s/n Camino publico Zapallar Papudo Ruta F30 E,", "STDO_DESCR": "DECRETO NOTIFICADO", "DOC_NUMERO": "177", "ANIO_DOC": "09/11/2012", "ELM_CODIGO": 456286, "ELM_NOMBRE": "LVR045", "FRECUENCIA": 2600, "TECNOLOGIA": "LTE", "POINT_X": -71.458611111, "POINT_Y": -32.519444444, "COD_REG": 5, "COD_PROV": 54, "COD_COM": 5403, "COD_SSUBCU": 5300}}, {"type": "Feature", "geometry": {"type": "Point", "coordinates": [-71.45833060000004, -32.51943890000002]}, "properties": {"CUT_REG": "05", "CUT_PROV": "054", "CUT_COM": "05403", "REGION": "Valpara\u00edso", "PROVINCIA": "Petorca", "COMUNA": "Papudo", "COD_CUEN": "053", "COD_SUBC": "0530", "COD_SSUBC": "05300", "NOM_SSUBC": "Costera entre Estero Ligua y Estero Catapilco", "ALIAS": "CLARO CHILE S.A.", "TISO_DESCR": "Torre Auto Soportada", "SOPO_ALTUR": 18, "DTE_DIRECC": "Cerro El Chorrillo", "STDO_DESCR": "DECRETO NOTIFICADO", "DOC_NUMERO": "567", "ANIO_DOC": "03/10/2006", "ELM_CODIGO": 20406, "ELM_NOMBRE": "Papudo", "FRECUENCIA": 850, "TECNOLOGIA": "GSM", "POINT_X": -71.4583306, "POINT_Y": -32.5194389, "COD_REG": 5, "COD_PROV": 54, "COD_COM": 5403, "COD_SSUBCU": 5300}}, {"type": "Feature", "geometry": {"type": "Point", "coordinates": [-71.45833060000004, -32.51943890000002]}, "properties": {"CUT_REG": "05", "CUT_PROV": "054", "CUT_COM": "05403", "REGION": "Valpara\u00edso", "PROVINCIA": "Petorca", "COMUNA": "Papudo", "COD_CUEN": "053", "COD_SUBC": "0530", "COD_SSUBC": "05300", "NOM_SSUBC": "Costera entre Estero Ligua y Estero Catapilco", "ALIAS": "CLARO CHILE S.A.", "TISO_DESCR": "Torre Auto Soportada", "SOPO_ALTUR": 18, "DTE_DIRECC": "Cerro El Chorrillo", "STDO_DESCR": "DECRETO NOTIFICADO", "DOC_NUMERO": "641", "ANIO_DOC": "05/07/2007", "ELM_CODIGO": 30704, "ELM_NOMBRE": "Papudo", "FRECUENCIA": 850, "TECNOLOGIA": "UMTS", "POINT_X": -71.4583306, "POINT_Y": -32.5194389, "COD_REG": 5, "COD_PROV": 54, "COD_COM": 5403, "COD_SSUBCU": 5300}}, {"type": "Feature", "geometry": {"type": "Point", "coordinates": [-71.45833060000004, -32.51943890000002]}, "properties": {"CUT_REG": "05", "CUT_PROV": "054", "CUT_COM": "05403", "REGION": "Valpara\u00edso", "PROVINCIA": "Petorca", "COMUNA": "Papudo", "COD_CUEN": "053", "COD_SUBC": "0530", "COD_SSUBC": "05300", "NOM_SSUBC": "Costera entre Estero Ligua y Estero Catapilco", "ALIAS": "CLARO CHILE S.A.", "TISO_DESCR": "Torre Auto Soportada", "SOPO_ALTUR": 18, "DTE_DIRECC": "Cerro El Chorrillo, Zapallar", "STDO_DESCR": "DECRETO EXENTO NOTIFICADO", "DOC_NUMERO": "651", "ANIO_DOC": "07/11/2013", "ELM_CODIGO": 15868, "ELM_NOMBRE": "Papudo", "FRECUENCIA": 1900, "TECNOLOGIA": "GSM", "POINT_X": -71.4583306, "POINT_Y": -32.5194389, "COD_REG": 5, "COD_PROV": 54, "COD_COM": 5403, "COD_SSUBCU": 5300}}, {"type": "Feature", "geometry": {"type": "Point", "coordinates": [-71.45833060000004, -32.51943890000002]}, "properties": {"CUT_REG": "05", "CUT_PROV": "054", "CUT_COM": "05403", "REGION": "Valpara\u00edso", "PROVINCIA": "Petorca", "COMUNA": "Papudo", "COD_CUEN": "053", "COD_SUBC": "0530", "COD_SSUBC": "05300", "NOM_SSUBC": "Costera entre Estero Ligua y Estero Catapilco", "ALIAS": "CLARO CHILE S.A.", "TISO_DESCR": "Torre Auto Soportada", "SOPO_ALTUR": 18, "DTE_DIRECC": "Cerro El Chorrillo", "STDO_DESCR": "DECRETO NOTIFICADO", "DOC_NUMERO": "744", "ANIO_DOC": "12/12/2003", "ELM_CODIGO": 400713, "ELM_NOMBRE": "Papudo", "FRECUENCIA": 1900, "TECNOLOGIA": "CDMA2000", "POINT_X": -71.4583306, "POINT_Y": -32.5194389, "COD_REG": 5, "COD_PROV": 54, "COD_COM": 5403, "COD_SSUBCU": 5300}}, {"type": "Feature", "geometry": {"type": "Point", "coordinates": [-71.45833060000004, -32.51943890000002]}, "properties": {"CUT_REG": "05", "CUT_PROV": "054", "CUT_COM": "05403", "REGION": "Valpara\u00edso", "PROVINCIA": "Petorca", "COMUNA": "Papudo", "COD_CUEN": "053", "COD_SUBC": "0530", "COD_SSUBC": "05300", "NOM_SSUBC": "Costera entre Estero Ligua y Estero Catapilco", "ALIAS": "Claro Serv. Empresariales", "TISO_DESCR": "Torre Auto Soportada", "SOPO_ALTUR": 18, "DTE_DIRECC": "Cerro El Chorrillo", "STDO_DESCR": "DECRETO NOTIFICADO", "DOC_NUMERO": "78", "ANIO_DOC": "30/05/2013", "ELM_CODIGO": 440495, "ELM_NOMBRE": "Papudo", "FRECUENCIA": 2600, "TECNOLOGIA": "LTE", "POINT_X": -71.4583306, "POINT_Y": -32.5194389, "COD_REG": 5, "COD_PROV": 54, "COD_COM": 5403, "COD_SSUBCU": 5300}}, {"type": "Feature", "geometry": {"type": "Point", "coordinates": [-71.45777777799995, -32.519166666999965]}, "properties": {"CUT_REG": "05", "CUT_PROV": "054", "CUT_COM": "05403", "REGION": "Valpara\u00edso", "PROVINCIA": "Petorca", "COMUNA": "Papudo", "COD_CUEN": "053", "COD_SUBC": "0530", "COD_SSUBC": "05300", "NOM_SSUBC": "Costera entre Estero Ligua y Estero Catapilco", "ALIAS": "MOVISTAR MOVIL", "TISO_DESCR": "Torre Auto Soportada", "SOPO_ALTUR": 15, "DTE_DIRECC": "Papudo", "STDO_DESCR": "DECRETO NOTIFICADO", "DOC_NUMERO": "184", "ANIO_DOC": "23/04/1999", "ELM_CODIGO": 398382, "ELM_NOMBRE": "Papudo", "FRECUENCIA": 850, "TECNOLOGIA": "GSM", "POINT_X": -71.457777778, "POINT_Y": -32.519166667, "COD_REG": 5, "COD_PROV": 54, "COD_COM": 5403, "COD_SSUBCU": 5300}}, {"type": "Feature", "geometry": {"type": "Point", "coordinates": [-71.45777777799995, -32.519166666999965]}, "properties": {"CUT_REG": "05", "CUT_PROV": "054", "CUT_COM": "05403", "REGION": "Valpara\u00edso", "PROVINCIA": "Petorca", "COMUNA": "Papudo", "COD_CUEN": "053", "COD_SUBC": "0530", "COD_SSUBC": "05300", "NOM_SSUBC": "Costera entre Estero Ligua y Estero Catapilco", "ALIAS": "MOVISTAR MOVIL", "TISO_DESCR": "Torre Auto Soportada", "SOPO_ALTUR": 15, "DTE_DIRECC": "Cerro Pite, Hacienda Pullally", "STDO_DESCR": "DECRETO NOTIFICADO", "DOC_NUMERO": "550", "ANIO_DOC": "12/06/2007", "ELM_CODIGO": 10921, "ELM_NOMBRE": "Papudo", "FRECUENCIA": 1900, "TECNOLOGIA": "GSM", "POINT_X": -71.457777778, "POINT_Y": -32.519166667, "COD_REG": 5, "COD_PROV": 54, "COD_COM": 5403, "COD_SSUBCU": 5300}}, {"type": "Feature", "geometry": {"type": "Point", "coordinates": [-71.45166666699996, -32.51000000000001]}, "properties": {"CUT_REG": "05", "CUT_PROV": "054", "CUT_COM": "05403", "REGION": "Valpara\u00edso", "PROVINCIA": "Petorca", "COMUNA": "Papudo", "COD_CUEN": "053", "COD_SUBC": "0530", "COD_SSUBC": "05300", "NOM_SSUBC": "Costera entre Estero Ligua y Estero Catapilco", "ALIAS": "ENTEL PCS", "TISO_DESCR": "Torre Auto Soportada", "SOPO_ALTUR": 30, "DTE_DIRECC": "AV. CIRCUNVALACION S/N EL MIRADOR DEL FRANCES", "STDO_DESCR": "DECRETO NOTIFICADO", "DOC_NUMERO": "143", "ANIO_DOC": "15/03/2002", "ELM_CODIGO": 11871, "ELM_NOMBRE": "Papudo", "FRECUENCIA": 1900, "TECNOLOGIA": "GSM", "POINT_X": -71.451666667, "POINT_Y": -32.51, "COD_REG": 5, "COD_PROV": 54, "COD_COM": 5403, "COD_SSUBCU": 5300}}, {"type": "Feature", "geometry": {"type": "Point", "coordinates": [-71.45166666699996, -32.51000000000001]}, "properties": {"CUT_REG": "05", "CUT_PROV": "054", "CUT_COM": "05403", "REGION": "Valpara\u00edso", "PROVINCIA": "Petorca", "COMUNA": "Papudo", "COD_CUEN": "053", "COD_SUBC": "0530", "COD_SSUBC": "05300", "NOM_SSUBC": "Costera entre Estero Ligua y Estero Catapilco", "ALIAS": "ENTEL PCS", "TISO_DESCR": "Torre Auto Soportada", "SOPO_ALTUR": 30, "DTE_DIRECC": "AV. CIRCUNVALACI\u00d3N S/N", "STDO_DESCR": "DECRETO NOTIFICADO", "DOC_NUMERO": "113", "ANIO_DOC": "19/02/2007", "ELM_CODIGO": 25574, "ELM_NOMBRE": "Papudo", "FRECUENCIA": 1900, "TECNOLOGIA": "UMTS", "POINT_X": -71.451666667, "POINT_Y": -32.51, "COD_REG": 5, "COD_PROV": 54, "COD_COM": 5403, "COD_SSUBCU": 5300}}, {"type": "Feature", "geometry": {"type": "Point", "coordinates": [-71.45166666699996, -32.50944444399997]}, "properties": {"CUT_REG": "05", "CUT_PROV": "054", "CUT_COM": "05403", "REGION": "Valpara\u00edso", "PROVINCIA": "Petorca", "COMUNA": "Papudo", "COD_CUEN": "053", "COD_SUBC": "0530", "COD_SSUBC": "05300", "NOM_SSUBC": "Costera entre Estero Ligua y Estero Catapilco", "ALIAS": "Movistar", "TISO_DESCR": "Torre Auto Soportada", "SOPO_ALTUR": 42, "DTE_DIRECC": "Av. Circunvalaci\u00f3n, Sector Mirador del Frances", "STDO_DESCR": "DECRETO NOTIFICADO", "DOC_NUMERO": "488", "ANIO_DOC": "06/12/2005", "ELM_CODIGO": 14106, "ELM_NOMBRE": "Papudo", "FRECUENCIA": 1900, "TECNOLOGIA": "GSM", "POINT_X": -71.451666667, "POINT_Y": -32.509444444, "COD_REG": 5, "COD_PROV": 54, "COD_COM": 5403, "COD_SSUBCU": 5300}}, {"type": "Feature", "geometry": {"type": "Point", "coordinates": [-71.45166666699996, -32.50944444399997]}, "properties": {"CUT_REG": "05", "CUT_PROV": "054", "CUT_COM": "05403", "REGION": "Valpara\u00edso", "PROVINCIA": "Petorca", "COMUNA": "Papudo", "COD_CUEN": "053", "COD_SUBC": "0530", "COD_SSUBC": "05300", "NOM_SSUBC": "Costera entre Estero Ligua y Estero Catapilco", "ALIAS": "Movistar", "TISO_DESCR": "Torre Auto Soportada", "SOPO_ALTUR": 42, "DTE_DIRECC": "Mirador del Frances", "STDO_DESCR": "DECRETO NOTIFICADO", "DOC_NUMERO": "451", "ANIO_DOC": "21/11/2005", "ELM_CODIGO": 14093, "ELM_NOMBRE": "Papudo", "FRECUENCIA": 1900, "TECNOLOGIA": "GSM", "POINT_X": -71.451666667, "POINT_Y": -32.509444444, "COD_REG": 5, "COD_PROV": 54, "COD_COM": 5403, "COD_SSUBCU": 5300}}, {"type": "Feature", "geometry": {"type": "Point", "coordinates": [-71.29805555600004, -32.49222222199999]}, "properties": {"CUT_REG": "05", "CUT_PROV": "054", "CUT_COM": "05403", "REGION": "Valpara\u00edso", "PROVINCIA": "Petorca", "COMUNA": "Papudo", "COD_CUEN": "052", "COD_SUBC": "0522", "COD_SSUBC": "05221", "NOM_SSUBC": "Rio Ligua Entre Estero La Patagua y Desembocadura", "ALIAS": "Wom", "TISO_DESCR": "Torre Auto Soportada", "SOPO_ALTUR": 26, "DTE_DIRECC": "C\u00ba La Mestiza, Km. 146, Ruta 5 Norte", "STDO_DESCR": "DECRETO EXENTO NOTIFICADO", "DOC_NUMERO": "561", "ANIO_DOC": "28/06/2012", "ELM_CODIGO": 60901, "ELM_NOMBRE": "VAL_3G_125", "FRECUENCIA": 2100, "TECNOLOGIA": "GSM-UMTS", "POINT_X": -71.298055556, "POINT_Y": -32.492222222, "COD_REG": 5, "COD_PROV": 54, "COD_COM": 5403, "COD_SSUBCU": 5221}}, {"type": "Feature", "geometry": {"type": "Point", "coordinates": [-71.35416666700002, -32.45999999999995]}, "properties": {"CUT_REG": "05", "CUT_PROV": "054", "CUT_COM": "05403", "REGION": "Valpara\u00edso", "PROVINCIA": "Petorca", "COMUNA": "Papudo", "COD_CUEN": "053", "COD_SUBC": "0530", "COD_SSUBC": "05300", "NOM_SSUBC": "Costera entre Estero Ligua y Estero Catapilco", "ALIAS": "ENTEL PCS", "TISO_DESCR": "Torre Ventada", "SOPO_ALTUR": 30, "DTE_DIRECC": "APARTADO 6-B, LAS SALINAS DE PULLALLI", "STDO_DESCR": "DECRETO EXENTO NOTIFICADO", "DOC_NUMERO": "18", "ANIO_DOC": "05/01/2009", "ELM_CODIGO": 41721, "ELM_NOMBRE": "Ruta Papudo - Pullalli Alt. 2", "FRECUENCIA": 1900, "TECNOLOGIA": "GSM", "POINT_X": -71.354166667, "POINT_Y": -32.46, "COD_REG": 5, "COD_PROV": 54, "COD_COM": 5403, "COD_SSUBCU": 5300}}, {"type": "Feature", "geometry": {"type": "Point", "coordinates": [-71.32944444399996, -32.44666666699995]}, "properties": {"CUT_REG": "05", "CUT_PROV": "054", "CUT_COM": "05403", "REGION": "Valpara\u00edso", "PROVINCIA": "Petorca", "COMUNA": "Papudo", "COD_CUEN": "052", "COD_SUBC": "0522", "COD_SSUBC": "05221", "NOM_SSUBC": "Rio Ligua Entre Estero La Patagua y Desembocadura", "ALIAS": "ENTEL PCS", "TISO_DESCR": "Torre Ventada", "SOPO_ALTUR": 30, "DTE_DIRECC": "CERRO TRARO", "STDO_DESCR": "DECRETO EXENTO NOTIFICADO", "DOC_NUMERO": "592", "ANIO_DOC": "06/07/2010", "ELM_CODIGO": 49415, "ELM_NOMBRE": "Quinquimo", "FRECUENCIA": 1900, "TECNOLOGIA": "GSM", "POINT_X": -71.329444444, "POINT_Y": -32.446666667, "COD_REG": 5, "COD_PROV": 54, "COD_COM": 5403, "COD_SSUBCU": 5221}}, {"type": "Feature", "geometry": {"type": "Point", "coordinates": [-71.32944444399996, -32.44666666699995]}, "properties": {"CUT_REG": "05", "CUT_PROV": "054", "CUT_COM": "05403", "REGION": "Valpara\u00edso", "PROVINCIA": "Petorca", "COMUNA": "Papudo", "COD_CUEN": "052", "COD_SUBC": "0522", "COD_SSUBC": "05221", "NOM_SSUBC": "Rio Ligua Entre Estero La Patagua y Desembocadura", "ALIAS": "ENTEL PCS", "TISO_DESCR": "Torre Ventada", "SOPO_ALTUR": 30, "DTE_DIRECC": "Cerro Traro", "STDO_DESCR": "DECRETO NOTIFICADO", "DOC_NUMERO": "732", "ANIO_DOC": "15/10/2002", "ELM_CODIGO": 12071, "ELM_NOMBRE": "Quinquimo", "FRECUENCIA": 1900, "TECNOLOGIA": "GSM", "POINT_X": -71.329444444, "POINT_Y": -32.446666667, "COD_REG": 5, "COD_PROV": 54, "COD_COM": 5403, "COD_SSUBCU": 5221}}, {"type": "Feature", "geometry": {"type": "Point", "coordinates": [-71.32963890000005, -32.44621939999998]}, "properties": {"CUT_REG": "05", "CUT_PROV": "054", "CUT_COM": "05403", "REGION": "Valpara\u00edso", "PROVINCIA": "Petorca", "COMUNA": "Papudo", "COD_CUEN": "052", "COD_SUBC": "0522", "COD_SSUBC": "05221", "NOM_SSUBC": "Rio Ligua Entre Estero La Patagua y Desembocadura", "ALIAS": "CLARO CHILE S.A.", "TISO_DESCR": "Torre Auto Soportada", "SOPO_ALTUR": 42, "DTE_DIRECC": "Cerro El Traro, Ruta 5 norte, Km 156.", "STDO_DESCR": "DECRETO NOTIFICADO", "DOC_NUMERO": "398", "ANIO_DOC": "02/05/2007", "ELM_CODIGO": 27175, "ELM_NOMBRE": "Quinquimo", "FRECUENCIA": 850, "TECNOLOGIA": "GSM", "POINT_X": -71.3296389, "POINT_Y": -32.4462194, "COD_REG": 5, "COD_PROV": 54, "COD_COM": 5403, "COD_SSUBCU": 5221}}, {"type": "Feature", "geometry": {"type": "Point", "coordinates": [-71.32963890000005, -32.44621939999998]}, "properties": {"CUT_REG": "05", "CUT_PROV": "054", "CUT_COM": "05403", "REGION": "Valpara\u00edso", "PROVINCIA": "Petorca", "COMUNA": "Papudo", "COD_CUEN": "052", "COD_SUBC": "0522", "COD_SSUBC": "05221", "NOM_SSUBC": "Rio Ligua Entre Estero La Patagua y Desembocadura", "ALIAS": "CLARO CHILE S.A.", "TISO_DESCR": "Torre Auto Soportada", "SOPO_ALTUR": 42, "DTE_DIRECC": "Cerro El Traro, Ruta 5 norte, Km 156", "STDO_DESCR": "DECRETO NOTIFICADO", "DOC_NUMERO": "205", "ANIO_DOC": "25/04/2006", "ELM_CODIGO": 20850, "ELM_NOMBRE": "Quinquimo (Aly A)", "FRECUENCIA": 1900, "TECNOLOGIA": "GSM", "POINT_X": -71.3296389, "POINT_Y": -32.4462194, "COD_REG": 5, "COD_PROV": 54, "COD_COM": 5403, "COD_SSUBCU": 5221}}, {"type": "Feature", "geometry": {"type": "Point", "coordinates": [-71.32963890000005, -32.44621939999998]}, "properties": {"CUT_REG": "05", "CUT_PROV": "054", "CUT_COM": "05403", "REGION": "Valpara\u00edso", "PROVINCIA": "Petorca", "COMUNA": "Papudo", "COD_CUEN": "052", "COD_SUBC": "0522", "COD_SSUBC": "05221", "NOM_SSUBC": "Rio Ligua Entre Estero La Patagua y Desembocadura", "ALIAS": "Claro Serv. Empresariales", "TISO_DESCR": "Torre Auto Soportada", "SOPO_ALTUR": 42, "DTE_DIRECC": "Cerro El Traro, Ruta 5 norte, Km 156,", "STDO_DESCR": "DECRETO NOTIFICADO", "DOC_NUMERO": "78", "ANIO_DOC": "30/05/2013", "ELM_CODIGO": 440494, "ELM_NOMBRE": "Quinquimo", "FRECUENCIA": 2600, "TECNOLOGIA": "LTE", "POINT_X": -71.3296389, "POINT_Y": -32.4462194, "COD_REG": 5, "COD_PROV": 54, "COD_COM": 5403, "COD_SSUBCU": 5221}}, {"type": "Feature", "geometry": {"type": "Point", "coordinates": [-71.32972222200002, -32.44583333300002]}, "properties": {"CUT_REG": "05", "CUT_PROV": "054", "CUT_COM": "05403", "REGION": "Valpara\u00edso", "PROVINCIA": "Petorca", "COMUNA": "Papudo", "COD_CUEN": "052", "COD_SUBC": "0522", "COD_SSUBC": "05221", "NOM_SSUBC": "Rio Ligua Entre Estero La Patagua y Desembocadura", "ALIAS": "Movistar", "TISO_DESCR": "Torre Auto Soportada", "SOPO_ALTUR": 36, "DTE_DIRECC": "Camino a Papudo, km 2; desde Autopista 5 Norte. Cerro Traro", "STDO_DESCR": "DECRETO NOTIFICADO", "DOC_NUMERO": "595", "ANIO_DOC": "05/10/2004", "ELM_CODIGO": 13850, "ELM_NOMBRE": "QUINQUIMO", "FRECUENCIA": 1900, "TECNOLOGIA": "GSM", "POINT_X": -71.329722222, "POINT_Y": -32.445833333, "COD_REG": 5, "COD_PROV": 54, "COD_COM": 5403, "COD_SSUBCU": 5221}}, {"type": "Feature", "geometry": {"type": "Point", "coordinates": [-71.32972222200002, -32.44583333300002]}, "properties": {"CUT_REG": "05", "CUT_PROV": "054", "CUT_COM": "05403", "REGION": "Valpara\u00edso", "PROVINCIA": "Petorca", "COMUNA": "Papudo", "COD_CUEN": "052", "COD_SUBC": "0522", "COD_SSUBC": "05221", "NOM_SSUBC": "Rio Ligua Entre Estero La Patagua y Desembocadura", "ALIAS": "Movistar", "TISO_DESCR": "Torre Auto Soportada", "SOPO_ALTUR": 36, "DTE_DIRECC": "Camino a Papudo, km 2; desde Autopista 5 Norte. Cerro Traro", "STDO_DESCR": "DECRETO NOTIFICADO", "DOC_NUMERO": "594", "ANIO_DOC": "05/10/2004", "ELM_CODIGO": 21889, "ELM_NOMBRE": "Quinquimo", "FRECUENCIA": 1900, "TECNOLOGIA": "GSM", "POINT_X": -71.329722222, "POINT_Y": -32.445833333, "COD_REG": 5, "COD_PROV": 54, "COD_COM": 5403, "COD_SSUBCU": 5221}}, {"type": "Feature", "geometry": {"type": "Point", "coordinates": [-71.32972222200002, -32.44583333300002]}, "properties": {"CUT_REG": "05", "CUT_PROV": "054", "CUT_COM": "05403", "REGION": "Valpara\u00edso", "PROVINCIA": "Petorca", "COMUNA": "Papudo", "COD_CUEN": "052", "COD_SUBC": "0522", "COD_SSUBC": "05221", "NOM_SSUBC": "Rio Ligua Entre Estero La Patagua y Desembocadura", "ALIAS": "Wom", "TISO_DESCR": "Torre Auto Soportada", "SOPO_ALTUR": 31, "DTE_DIRECC": "Cerro El Traro, Ruta 5 Norte, Km 156", "STDO_DESCR": "DECRETO EXENTO NOTIFICADO", "DOC_NUMERO": "600", "ANIO_DOC": "05/07/2012", "ELM_CODIGO": 395503, "ELM_NOMBRE": "VAL_3G_127", "FRECUENCIA": 2100, "TECNOLOGIA": "UMTS", "POINT_X": -71.329722222, "POINT_Y": -32.445833333, "COD_REG": 5, "COD_PROV": 54, "COD_COM": 5403, "COD_SSUBCU": 5221}}, {"type": "Feature", "geometry": {"type": "Point", "coordinates": [-71.32972222200002, -32.44583333300002]}, "properties": {"CUT_REG": "05", "CUT_PROV": "054", "CUT_COM": "05403", "REGION": "Valpara\u00edso", "PROVINCIA": "Petorca", "COMUNA": "Papudo", "COD_CUEN": "052", "COD_SUBC": "0522", "COD_SSUBC": "05221", "NOM_SSUBC": "Rio Ligua Entre Estero La Patagua y Desembocadura", "ALIAS": "Wom", "TISO_DESCR": "Torre Auto Soportada", "SOPO_ALTUR": 31, "DTE_DIRECC": "C\u00b0 El Trato Ruta F 30 Km 2", "STDO_DESCR": "DECRETO EXENTO NOTIFICADO", "DOC_NUMERO": "838", "ANIO_DOC": "01/12/2014", "ELM_CODIGO": 60576, "ELM_NOMBRE": "VAL_3G_127", "FRECUENCIA": 2100, "TECNOLOGIA": "UMTS", "POINT_X": -71.329722222, "POINT_Y": -32.445833333, "COD_REG": 5, "COD_PROV": 54, "COD_COM": 5403, "COD_SSUBCU": 5221}}]}